gecosistema_gdal/__init__.py
gecosistema_gdal/gdal_numpy.py
gecosistema_gdal/gdal_sparse.py
gecosistema_gdal/gdal_utils.py
gecosistema_gdal/gdalwarp.py
gecosistema_gdal/ogr_utils.py
gecosistema_gdal/raster_like.py
gecosistema_gdal/rasterlike.py
gecosistema_gdal/taudem.py
gecosistema_gdal-0.0.171.dist-info/LICENSE
gecosistema_gdal-0.0.171.dist-info/METADATA
gecosistema_gdal-0.0.171.dist-info/WHEEL
gecosistema_gdal-0.0.171.dist-info/top_level.txt
gecosistema_gdal-0.0.171.dist-info/RECORD
