Metadata-Version: 2.1
Name: gecosistema-gdal
Version: 0.0.171
Summary: A core functions package
Home-page: https://github.com/valluzzi/gecosistema_gdal.git
Author: Valerio Luzzi
Author-email: valluzzi@gmail.com
License: UNKNOWN
Platform: UNKNOWN
Classifier: Programming Language :: Python :: 3
Classifier: License :: OSI Approved :: MIT License
Classifier: Operating System :: OS Independent
License-File: LICENSE
Requires-Dist: rtree
Requires-Dist: gecosistema-core
Requires-Dist: gdal
